[   {
		"videoid": "3mHBiu_JOOw",
		"startTime": "",
		"endTime": ""
	},
	{
		"videoid": "QYp28tEAVvs",
		"startTime": "",
		"endTime": ""
	},
	{
		"videoid": "Q6TLWqn82J4",
		"startTime": "",
		"endTime": ""
	},
	{
		"videoid": "1QWEPdgS3As",
		"startTime": "",
		"endTime": ""
	},
	{
		"videoid": "cM4kqL13jGM",
		"startTime": "",
		"endTime": ""
	},
	{
		"videoid": "fXJc2NYwHjw",
		"startTime": "",
		"endTime": ""
	},
	{
		"videoid": "a-mAK3uB2_0",
		"startTime": "",
		"endTime": ""
	},
	{
		"videoid": "cmXZOI7cM0M",
		"startTime": "",
		"endTime": ""
	},
	{
		"videoid": "jQ-RrGCSa2M",
		"startTime": "",
		"endTime": ""
	},
	{
		"videoid": "PMbELEUfmIA",
		"startTime": "",
		"endTime": ""
	},
	{
		"videoid": "P800UWoE9xs",
		"startTime": "",
		"endTime": ""
	},
	{
		"videoid": "WWMjRMJ0dTI",
		"startTime": "",
		"endTime": ""
	},
	{
		"videoid": "VC4ORS5n9Hg",
		"startTime": "",
		"endTime": ""
	},
	{
		"videoid": "3hOZaTGnHU4",
		"startTime": "",
		"endTime": ""
	},
	{
		"videoid": "2TN-kDEKxF0",
		"startTime": "",
		"endTime": ""
	},
	{
		"videoid": "N_9GuiE5Fck",
		"startTime": "",
		"endTime": ""
	},
	{
		"videoid": "h1vKOchATXs",
		"startTime": "",
		"endTime": ""
	},
	{
		"videoid": "oVDfyc2lh4Q",
		"startTime": "",
		"endTime": ""
	},
	{
		"videoid": "auhwI00iKWg",
		"startTime": "",
		"endTime": ""
	},
	{
		"videoid": "9aofoBrFNdg",
		"startTime": "",
		"endTime": ""
	},
	{
		"videoid": "6Y1Emb7Jyks",
		"startTime": "",
		"endTime": ""
	},
	{
		"videoid": "k7iAvR_AKzg",
		"startTime": "",
		"endTime": ""
	},
	{
		"videoid": "E7t8eoA_1jQ",
		"startTime": "",
		"endTime": ""
	},
	{
		"videoid": "HjNTu8jdukA",
		"startTime": "",
		"endTime": ""
	},
	{
		"videoid": "DhPtRA7zieE",
		"startTime": "",
		"endTime": ""
	},
	{
		"videoid": "AiwvPmRTv6M",
		"startTime": "",
		"endTime": ""
	},
	{
		"videoid": "7Xue-dOOLiY",
		"startTime": "45",
		"endTime": "274"
	},
	{
		"videoid": "9Ww-TQUeA3E",
		"startTime": "",
		"endTime": ""
	},
	{
		"videoid": "qKdS2WHUsIE",
		"startTime": "",
		"endTime": ""
	},
	{
		"videoid": "E58qLXBfLrs",
		"startTime": "",
		"endTime": ""
	},
	{
		"videoid": "MYF7H_fpc-g",
		"startTime": "",
		"endTime": ""
	},
	{
		"videoid": "IAHgyLOudXI",
		"startTime": "",
		"endTime": ""
	},
	{
		"videoid": "Gl83mI69nX4",
		"startTime": "",
		"endTime": ""
	},
	{
		"videoid": "Ge4BEdyZ8bM",
		"startTime": "",
		"endTime": ""
	},
	{
		"videoid": "C3m3t_PxiUI",
		"startTime": "",
		"endTime": ""
	},
	{
		"videoid": "RM7lw0Ovzq0",
		"startTime": "",
		"endTime": ""
	},
	{
		"videoid": "9f5zD7ZSNpQ",
		"startTime": "",
		"endTime": ""
	},
	{
		"videoid": "PArF9k2SbQk",
		"startTime": "",
		"endTime": ""
	},
	{
		"videoid": "y7_eA6NZ9VQ",
		"startTime": "",
		"endTime": ""
	},
	{
		"videoid": "RSliJeVhMho",
		"startTime": "",
		"endTime": ""
	},
	{
		"videoid": "Bvzqa-fjmFk",
		"startTime": "",
		"endTime": ""
	},
	{
		"videoid": "gBXdsi4jFHU",
		"startTime": "",
		"endTime": ""
	},
	{
		"videoid": "YL3ZKOw05T4",
		"startTime": "",
		"endTime": ""
	},
	{
		"videoid": "OGy4bmG5SJw",
		"startTime": "",
		"endTime": ""
	},
	{
		"videoid": "CssC-DY4lO8",
		"startTime": "",
		"endTime": ""
	},
	{
		"videoid": "R0IUR4gkPIE",
		"startTime": "",
		"endTime": ""
	},
	{
		"videoid": "SsKT0s5J8ko",
		"startTime": "",
		"endTime": ""
	},
	{
		"videoid": "UCU6ZcNEmOc",
		"startTime": "",
		"endTime": ""
	},
	{
		"videoid": "WpQjN7yQ_8c",
		"startTime": "",
		"endTime": ""
	},
	{
		"videoid": "AfzItk8XGD4",
		"startTime": "",
		"endTime": ""
	},
	{
		"videoid": "c9VQye6P8k0",
		"startTime": "",
		"endTime": ""
	},
	{
		"videoid": "e5PnuIRnJW8",
		"startTime": "",
		"endTime": ""
	},
	{
		"videoid": "HCDYgZM5yq0",
		"startTime": "",
		"endTime": ""
	},
	{
		"videoid": "y9lNbNGbo24",
		"startTime": "",
		"endTime": ""
	},
	{
		"videoid": "hxce_qvhi5I",
		"startTime": "",
		"endTime": ""
	},
	{
		"videoid": "x4NtdEuJ75k",
		"startTime": "",
		"endTime": ""
	},
	{
		"videoid": "CMJH2XWBQGU",
		"startTime": "",
		"endTime": ""
	},
	{
		"videoid": "JCOURZ-yx4E",
		"startTime": "",
		"endTime": ""
	},
	{
		"videoid": "h2zgB93KANE",
		"startTime": "",
		"endTime": ""
	},
	{
		"videoid": "P8-9mY-JACM",
		"startTime": "",
		"endTime": ""
	},
	{
		"videoid": "_qzacv8dtb4",
		"startTime": "",
		"endTime": ""
	},
	{
		"videoid": "WHRnvjCkTsw",
		"startTime": "",
		"endTime": ""
	},
	{
		"videoid": "qmj1q67NDAk",
		"startTime": "",
		"endTime": ""
	},
	{
		"videoid": "9aofoBrFNdg",
		"startTime": "",
		"endTime": ""
	},
	{
		"videoid": "h4UqMyldS7Q",
		"startTime": "",
		"endTime": ""
	},
	{
		"videoid": "_JZom_gVfuw",
		"startTime": "",
		"endTime": ""
	},
	{
		"videoid": "PBsjggc5jHM",
		"startTime": "",
		"endTime": ""
	},
	{
		"videoid": "qORYO0atB6g",
		"startTime": "",
		"endTime": ""
	},
	{
		"videoid": "eBShN8qT4lk",
		"startTime": "",
		"endTime": ""
	},
	{
		"videoid": "4B_UYYPb-Gk",
		"startTime": "",
		"endTime": ""
	},
	{
		"videoid": "O3pyCGnZzYA",
		"startTime": "",
		"endTime": ""
	},
	{
		"videoid": "15UffN8eilI",
		"startTime": "",
		"endTime": ""
	},
	{
		"videoid": "uB1D9wWxd2w",
		"startTime": "",
		"endTime": ""
	},
	{
		"videoid": "-TN6zl3KSOs",
		"startTime": "",
		"endTime": ""
	},
	{
		"videoid": "ckprPLMXj5Y",
		"startTime": "",
		"endTime": ""
	},
	{
		"videoid": "lKkPkK4s6pI",
		"startTime": "",
		"endTime": ""
	},
	{
		"videoid": "lynKqRsZ7lU",
		"startTime": "",
		"endTime": ""
	},
	{
		"videoid": "QJUSUcua-e4",
		"startTime": "",
		"endTime": ""
	},
	{
		"videoid": "5souw4K5UQc",
		"startTime": "",
		"endTime": ""
	},
	{
		"videoid": "UUw8i7k1mwc",
		"startTime": "",
		"endTime": ""
	},
	{
		"videoid": "igLJ7PVnrBU",
		"startTime": "",
		"endTime": ""
	},
	{
		"videoid": "tMgkt9jdjTU",
		"startTime": "",
		"endTime": ""
	},
	{
		"videoid": "KesAaLs7NvQ",
		"startTime": "",
		"endTime": ""
	},
	{
		"videoid": "a8Ra0p1CRZg",
		"startTime": "",
		"endTime": ""
	},
	{
		"videoid": "0IYght7FGdg",
		"startTime": "",
		"endTime": ""
	}
]