[ {
		"videoid": "9OFpfTd0EIs"
	},
	{
		"videoid": "djV11Xbc914"
	},
	{
		"videoid": "OMOGaugKpzs"
	},
	{
		"videoid": "n4RjJKxsamQ"
	},
	{
		"videoid": "fJ9rUzIMcZQ"
	},
	{
		"videoid": "PIb6AZdTr-A"
	},
	{
		"videoid": "lDK9QqIzhwk"
	},
	{
		"videoid": "Zi_XLOBDo_Y"
	},
	{
		"videoid": "9jK-NcRmVcw"
	},
	{
		"videoid": "dQw4w9WgXcQ"
	},
	{
		"videoid": "Rbm6GXllBiw"
	},
	{
		"videoid": "xwtdhWltSIg"
	},
	{
		"videoid": "btPJPFnesV4"
	},
	{
		"videoid": "oRdxUFDoQe0"
	},
	{
		"videoid": "v2AC41dglnM"
	},
	{
		"videoid": "dsUXAEzaC3Q"
	},
	{
		"videoid": "HzZ_urpj4As"
	},
	{
		"videoid": "lcOxhH8N3Bo"
	},
	{
		"videoid": "pAgnJDJN4VA"
	},
	{
		"videoid": "YR5ApYxkU-U"
	},
	{
		"videoid": "o1tj2zJ2Wvg"
	},
	{
		"videoid": "Qt2mbGP6vFI"
	},
	{
		"videoid": "t1TcDHrkQYg"
	},
	{
		"videoid": "k2C5TjS2sh4"
	},
	{
		"videoid": "VdQY7BusJNU"
	},
	{
		"videoid": "loWXMtjUZWM"
	},
	{
		"videoid": "izGwDsrQ1eQ"
	},
	{
		"videoid": "FTQbiNvZqaY"
	},
	{
		"videoid": "rY0WxgSXdEE"
	},
	{
		"videoid": "qeMFqkcPYcg"
	},
	{
		"videoid": "eH3giaIzONA"
	},
	{
		"videoid": "WGU_4-5RaxU"
	},
	{
		"videoid": "etAIpkdhU9Q"
	},
	{
		"videoid": "XfR9iY5y94s"
	},
	{
		"videoid": "uPudE8nDog0"
	},
	{
		"videoid": "vCadcBR95oU"
	},
	{
		"videoid": "eFTLKWw542g"
	},
	{
		"videoid": "hCuMWrfXG4E"
	},
	{
		"videoid": "J9gKyRmic20"
	},
	{
		"videoid": "Lo2qQmj0_h4"
	},
	{
		"videoid": "l-O5IHVhWj0"
	},
	{
		"videoid": "4B_UYYPb-Gk"
	},
	{
		"videoid": "raNGeq3_DtM"
	},
	{
		"videoid": "t2mU6USTBRE"
	},
	{
		"videoid": "u1xrNaTO1bI"
	},
	{
		"videoid": "p3j2NYZ8FKs"
	},
	{
		"videoid": "s__rX_WL100"
	},
	{
		"videoid": "XcATvu5f9vE"
	},
	{
		"videoid": "7YvAYIJSSZY"
	},
	{
		"videoid": "VdphvuyaV_I"
	},
	{
		"videoid": "1lWJXDG2i0A"
	},
	{
		"videoid": "QYHxGBH6o4M"
	},
	{
		"videoid": "yRYFKcMa_Ek"
	},
	{
		"videoid": "VZt7J0iaUD0"
	},
	{
		"videoid": "ZcJjMnHoIBI"
	},
    {
		"videoid": "S1i5coU-0_Q"
	},
    {
		"videoid": "siwpn14IE7E"
	},
    {
		"videoid": "Ldyx3KHOFXw"
	},
    {
		"videoid": "TB54dZkzZOY"
	},
    {
		"videoid": "nKhN1t_7PEY"
	},
    {
		"videoid": "LvdLovAaYzM"
	},
    {
		"videoid": "xy4FXhkm6Nw"
	},
    {
		"videoid": "Z0GFRcFm-aY"
	},
    {
		"videoid": "MZjAantupsA"
	},
    {
		"videoid": "EPhWR4d3FJQ"
	},
    {
		"videoid": "nqAvFx3NxUM"
	},
    {
		"videoid": "m_9hfHvQSNo"
	},
    {
		"videoid": "s1ysoohV_zA"
	},
    {
		"videoid": "K1b8AhIsSYQ"
	},
    {
		"videoid": "Fe93CLbHjxQ"
	},
    {
		"videoid": "Iwuy4hHO3YQ"
	},
    {
		"videoid": "r0qBaBb1Y-U"
	},
    {
		"videoid": "SECVGN4Bsgg"
	},
    {
		"videoid": "Cv6tuzHUuuk"
	},
    {
		"videoid": "hXCKLJGLENs"
	},
    {
		"videoid": "iIpfWORQWhU"
	},
    {
		"videoid": "nUTXb-ga1fo"
	},
    {
		"videoid": "a1sf2CzEq0w"
	},
    {
		"videoid": "h04CH9YZcpI"
	},
    {
		"videoid": "AAZQaYKZMTI"
	},
    {
		"videoid": "3wxyN3z9PL4"
	},
    {
		"videoid": "LuyS9M8T03A"
	},
    {
		"videoid": "cX-8MHKuQ5I"
	},
    {
		"videoid": "X2LTL8KgKv8"
	},
    {
		"videoid": "IIEVqFB4WUo"
	},
    {
		"videoid": "NOGEyBeoBGM"
	},
    {
		"videoid": "fK9hK82r-AM"
	},
    {
		"videoid": "lAD6Obi7Cag"
	},
    {
		"videoid": "LB5YkmjalDg"
	},
    {
		"videoid": "9f16Fw_K45s"
	},
    {
		"videoid": "N6uEMOeDZsA"
	},
    {
		"videoid": "2ssCL292DQA"
	},
    {
		"videoid": "rrJky8YuTr4"
	},
    {
		"videoid": "0sw54Pdh_m8"
	},
    {
		"videoid": "fFnOfpIJL0M"
	},
    {
		"videoid": "sS6t56U9tBg"
	},
    {
		"videoid": "CnVf1ZoCJSo"
	},
    {
		"videoid": "PBAl9cchQac"
	},
    {
		"videoid": "6WTdTwcmxyo"
	},
    {
		"videoid": "KCjMZMxNr-0"
	},
    {
		"videoid": "YgSVTdAtNYE"
	},
	{
		"videoid": "F93ywiGMDnQ"
	},
	{
		"videoid": "AIBv2GEnXlc"
	},
	{
		"videoid": "9hGcJA8fXvU"
	},
	{
		"videoid": "Zhi6nNYNOxQ"
	},
	{
		"videoid": "8qrriKcwvlY"
	},
	{
		"videoid": "vpIduDaggVA"
	},
	{
		"videoid": "jWMToInrke0"
	},
	{
		"videoid": "s_8KR-n2fBQ"
	},
	{
		"videoid": "16y1AkoZkmQ"
	},
	{
		"videoid": "f8OHybVhQwc"
	},
	{
		"videoid": "d-diB65scQU"
	},
	{
		"videoid": "aGCdLKXNF3w"
	},
	{
		"videoid": "Lrle0x_DHBM"
	},
	{
		"videoid": "RP0_8J7uxhs"
	},
	{
		"videoid": "Ye7FKc1JQe4"
	},
	{
		"videoid": "3GwjfUFyY6M"
	},
	{
		"videoid": "uMUQMSXLlHM"
	},
	{
		"videoid": "CsHiG-43Fzg"
	},
	{
		"videoid": "X5h02ZmeB5c"
	},
	{
		"videoid": "El1kgCqD7Xk"
	},
	{
		"videoid": "NEUX-HYRtUA"
	},
	{
		"videoid": "c5BL4RNFr58"
	},
	{
		"videoid": "s36eQwgPNSE"
	},
	{
		"videoid": "VAtGOESO7W8"
	},
	{
		"videoid": "IuwxZSIS__4"
	},
	{
		"videoid": "MzGnX-MbYE4"
	},
	{
		"videoid": "EHV0zs0kVGg"
	},
	{
		"videoid": "w0N4twV28Mw"
	},
	{
		"videoid": "9dZW1C3neao"
	},
	{
		"videoid": "dFtLONl4cNc"
	},
	{
		"videoid": "tY8B0uQpwZs"
	},
	{
		"videoid": "uc6f_2nPSX8"
	},
	{
		"videoid": "4OUnedMCCW0"
	},
	{
		"videoid": "V83JR2IoI8k"
	},
	{
		"videoid": "5IsSpAOD6K8"
	},
	{
		"videoid": "P5ZJui3aPoQ"
	},
	{
		"videoid": "iPUmE-tne5U"
	},
	{
		"videoid": "NNiie_zmSr8"
	},
	{
		"videoid": "FYH8DsU2WCk"
	},
	{
		"videoid": "r_GH6M7cUq4"
	},
	{
		"videoid": "GHhD4PD75zY"
	},
	{
		"videoid": "yVBB2upbVys"
	},
	{
		"videoid": "HGIkImLf11o"
	},
	{
		"videoid": "YSAqXEcgoZ4"
	},
	{
		"videoid": "49FB9hhoO6c"
	},
	{
		"videoid": "tVCUAXOBF7w"
	},
	{
		"videoid": "SHUb-xQMTOI"
	},
	{
		"videoid": "HvldypUz9w8"
	},
	{
		"videoid": "2twLJU_ggGI"
	},
	{
		"videoid": "zILmrAJgzSc"
	},
	{
		"videoid": "674KGKRQBPE"
	},
	{
		"videoid": "5BIElTtN6Fs"
	},
	{
		"videoid": "Dvgbk4MkHF8"
	},
	{
		"videoid": "lBykvBKMeec"
	},
    {
		"videoid": "nFgfQcCmbs0"
	},
    {
		"videoid": "UBAO9WcdrOM"
	},
    {
		"videoid": "NyaOYfpq9Fc"
	}
]